hello_world/__init__.py
hello_world/hello.py
joseph_hello_world-0.1.dist-info/DESCRIPTION.rst
joseph_hello_world-0.1.dist-info/METADATA
joseph_hello_world-0.1.dist-info/RECORD
joseph_hello_world-0.1.dist-info/WHEEL
joseph_hello_world-0.1.dist-info/entry_points.txt
joseph_hello_world-0.1.dist-info/metadata.json
joseph_hello_world-0.1.dist-info/top_level.txt
