Metadata-Version: 2.0
Name: joseph-hello-world
Version: 0.1
Summary: A hello world plugin for Joseph
Home-page: https://github.com/NiekKeijzer/HelloWorld
Author: Niek Keijzer
Author-email: info@niekkeijzer.com
License: UNKNOWN
Download-URL: https://github.com/NiekKeijzer/HelloWorld/archive/0.1.tar.gaz
Keywords: hello world,joseph
Platform: UNKNOWN
